LICENSE
MANIFEST.in
README.rst
requirements.txt
setup.py
pyutilsnrw/__init__.py
pyutilsnrw/get_genomes.py
pyutilsnrw/parse_pileup.py
pyutilsnrw/utils3_5.py
pyutilsnrw.egg-info/PKG-INFO
pyutilsnrw.egg-info/SOURCES.txt
pyutilsnrw.egg-info/dependency_links.txt
pyutilsnrw.egg-info/requires.txt
pyutilsnrw.egg-info/top_level.txt