Metadata-Version: 1.1
Name: pyutilsnrw
Version: 0.1.1
Summary: Python utils, by Nick
Home-page: https://github.com/nickp60/pyutilsnrw
Author: Nick Waters
Author-email: nickp60@gmail.com
License: MIT
Keywords: sample bioinformatics setuptools development
Platform: UNKNOWN
Classifier: Development Status :: 3 - Alpha
Classifier: Intended Audience :: Developers
Classifier: Topic :: Software Development :: Build Tools
Classifier: License :: OSI Approved :: MIT License
Classifier: Programming Language :: Python :: 3.5
Classifier: Programming Language :: Python :: 3.6
